<?xml version="1.0"?>
<CIM CIMVERSION="2.3" DTDVERSION="2.2"><DECLARATION><DECLGROUP><VALUE.OBJECT>
<CLASS SUPERCLASS="CIM_Dependency" NAME="CIM_DatabaseAdministrator"><QUALIFIER NAME="Association" TYPE="boolean"><VALUE>true</VALUE></QUALIFIER><QUALIFIER NAME="Version" TYPE="string"><VALUE>2.7.0</VALUE></QUALIFIER><QUALIFIER NAME="UMLPackagePath" TYPE="string"><VALUE>CIM::Database::System</VALUE></QUALIFIER><QUALIFIER NAME="Description" TYPE="string"><VALUE>The DatabaseAdministrator association identifies a UserEntity as a database administrator of a CommonDatabase. 
The current version of CIM includes a UserContact class that is concrete and extends from UserEntity. UserContact contains the information that is needed to contact a database administrator. The DatabaseAdministrator association should be implemented through the UserContact class in favor of creating a vendor-specific concrete class to define database administrator contact information for the database administrator.</VALUE></QUALIFIER><PROPERTY.REFERENCE CLASSORIGIN="CIM_DatabaseAdministrator" PROPAGATED="false" REFERENCECLASS="CIM_CommonDatabase" NAME="Antecedent"><QUALIFIER TOSUBCLASS="false" NAME="Override" TYPE="string"><VALUE>Antecedent</VALUE></QUALIFIER><QUALIFIER TRANSLATABLE="true" NAME="Description" TYPE="string"><VALUE>The database that is being administered.</VALUE></QUALIFIER><QUALIFIER OVERRIDABLE="false" NAME="Key" TYPE="boolean"><VALUE>true</VALUE></QUALIFIER></PROPERTY.REFERENCE><PROPERTY.REFERENCE CLASSORIGIN="CIM_DatabaseAdministrator" PROPAGATED="false" REFERENCECLASS="CIM_UserEntity" NAME="Dependent"><QUALIFIER TOSUBCLASS="false" NAME="Override" TYPE="string"><VALUE>Dependent</VALUE></QUALIFIER><QUALIFIER TRANSLATABLE="true" NAME="Description" TYPE="string"><VALUE>The user entity that is responsible for the administration of the database.</VALUE></QUALIFIER><QUALIFIER OVERRIDABLE="false" NAME="Key" TYPE="boolean"><VALUE>true</VALUE></QUALIFIER></PROPERTY.REFERENCE></CLASS></VALUE.OBJECT></DECLGROUP></DECLARATION></CIM>
