<?xml version="1.0"?>
<CIM CIMVERSION="2.3" DTDVERSION="2.2"><DECLARATION><DECLGROUP><VALUE.OBJECT>
<CLASS NAME="CIM_MemberOfCollection"><QUALIFIER OVERRIDABLE="false" NAME="Association" TYPE="boolean"><VALUE>true</VALUE></QUALIFIER><QUALIFIER OVERRIDABLE="false" NAME="Aggregation" TYPE="boolean"><VALUE>true</VALUE></QUALIFIER><QUALIFIER TOSUBCLASS="false" TRANSLATABLE="true" NAME="Version" TYPE="string"><VALUE>2.6.0</VALUE></QUALIFIER><QUALIFIER NAME="UMLPackagePath" TYPE="string"><VALUE>CIM::Core::Collection</VALUE></QUALIFIER><QUALIFIER TRANSLATABLE="true" NAME="Description" TYPE="string"><VALUE>CIM_MemberOfCollection is an aggregation used to establish membership of ManagedElements in a Collection.</VALUE></QUALIFIER><PROPERTY.REFERENCE CLASSORIGIN="CIM_MemberOfCollection" PROPAGATED="false" REFERENCECLASS="CIM_Collection" NAME="Collection"><QUALIFIER OVERRIDABLE="false" NAME="Key" TYPE="boolean"><VALUE>true</VALUE></QUALIFIER><QUALIFIER OVERRIDABLE="false" NAME="Aggregate" TYPE="boolean"><VALUE>true</VALUE></QUALIFIER><QUALIFIER TRANSLATABLE="true" NAME="Description" TYPE="string"><VALUE>The Collection that aggregates members.</VALUE></QUALIFIER></PROPERTY.REFERENCE><PROPERTY.REFERENCE CLASSORIGIN="CIM_MemberOfCollection" PROPAGATED="false" REFERENCECLASS="CIM_ManagedElement" NAME="Member"><QUALIFIER OVERRIDABLE="false" NAME="Key" TYPE="boolean"><VALUE>true</VALUE></QUALIFIER><QUALIFIER TRANSLATABLE="true" NAME="Description" TYPE="string"><VALUE>The aggregated member of the Collection.</VALUE></QUALIFIER></PROPERTY.REFERENCE></CLASS></VALUE.OBJECT></DECLGROUP></DECLARATION></CIM>
