<?xml version="1.0"?>
<CIM CIMVERSION="2.3" DTDVERSION="2.2"><DECLARATION><DECLGROUP><VALUE.OBJECT>
<CLASS SUPERCLASS="CIM_Dependency" NAME="PRS_SolutionCategory"><QUALIFIER NAME="Association" TYPE="boolean"><VALUE>true</VALUE></QUALIFIER><QUALIFIER NAME="Version" TYPE="string"><VALUE>2.6.0</VALUE></QUALIFIER><QUALIFIER NAME="UMLPackagePath" TYPE="string"><VALUE>PRS::Support</VALUE></QUALIFIER><QUALIFIER NAME="Description" TYPE="string"><VALUE>PRS_SolutionCategory associates PRS_Solution with a PRS_Category for classification purposes.</VALUE></QUALIFIER><PROPERTY.REFERENCE CLASSORIGIN="PRS_SolutionCategory" PROPAGATED="false" REFERENCECLASS="PRS_Solution" NAME="Antecedent"><QUALIFIER TOSUBCLASS="false" NAME="Override" TYPE="string"><VALUE>Antecedent</VALUE></QUALIFIER><QUALIFIER NAME="Min" TYPE="uint32"><VALUE>1</VALUE></QUALIFIER><QUALIFIER TRANSLATABLE="true" NAME="Description" TYPE="string"><VALUE>The PRS_Solution being classified.</VALUE></QUALIFIER><QUALIFIER OVERRIDABLE="false" NAME="Key" TYPE="boolean"><VALUE>true</VALUE></QUALIFIER></PROPERTY.REFERENCE><PROPERTY.REFERENCE CLASSORIGIN="PRS_SolutionCategory" PROPAGATED="false" REFERENCECLASS="PRS_Category" NAME="Dependent"><QUALIFIER TOSUBCLASS="false" NAME="Override" TYPE="string"><VALUE>Dependent</VALUE></QUALIFIER><QUALIFIER TRANSLATABLE="true" NAME="Description" TYPE="string"><VALUE>The specific PRS_Category being used to classify the Solution.</VALUE></QUALIFIER><QUALIFIER OVERRIDABLE="false" NAME="Key" TYPE="boolean"><VALUE>true</VALUE></QUALIFIER></PROPERTY.REFERENCE></CLASS></VALUE.OBJECT></DECLGROUP></DECLARATION></CIM>
